Metadata-Version: 2.1
Name: chess4fun
Version: 0.0.0a10
Summary: A Python App for Chess
Home-page: https://github.com/tank-overlord/chess4fun
Author: Tank Overlord
Author-email: TankOverLord88@gmail.com
License: LGPL-3.0
Platform: UNKNOWN
Classifier: Development Status :: 3 - Alpha
Classifier: Programming Language :: Python :: 3
Classifier: Programming Language :: Python :: 3.7
Classifier: Programming Language :: Python :: 3.8
Classifier: Programming Language :: Python :: 3.9
Classifier: License :: OSI Approved :: GNU Lesser General Public License v3 (LGPLv3)
Classifier: Operating System :: OS Independent
Requires-Python: >=3.7
Requires-Dist: chess (>=1.4.0)
Requires-Dist: pygame (>=2.0.1)
Requires-Dist: PySide2 (>=5.15.2)
